route_tracker/__init__.py
route_tracker/graph.py
route_tracker/io.py
route_tracker/projects.py
route_tracker/commands/__init__.py
route_tracker/commands/choices.py
route_tracker/commands/ending.py
route_tracker-0.1.1.dist-info/entry_points.txt
route_tracker-0.1.1.dist-info/LICENSE
route_tracker-0.1.1.dist-info/WHEEL
route_tracker-0.1.1.dist-info/METADATA
route_tracker-0.1.1.dist-info/RECORD
